gopy_ha_proton_drive-0.0.7.dist-info/licenses/LICENSE
proton/__init__.py
proton/_go_exec
proton/proton.py
proton/py.typed
gopy_ha_proton_drive-0.0.7.dist-info/METADATA
gopy_ha_proton_drive-0.0.7.dist-info/WHEEL
gopy_ha_proton_drive-0.0.7.dist-info/top_level.txt
gopy_ha_proton_drive-0.0.7.dist-info/RECORD
