Metadata-Version: 2.4
Name: gopy-ha-proton-drive
Version: 0.0.7
Summary: Python bindings for a Go wrapper around go-proton-api and Proton-API-Bridge
Author-email: Louis Brunner <pip@lbrunner.net>
License-Expression: MPL-2.0
Project-URL: Homepage, https://github.com/LouisBrunner/gopy-ha-proton-drive
Project-URL: Repository, https://github.com/LouisBrunner/gopy-ha-proton-drive
Keywords: proton,drive
Classifier: Programming Language :: Python :: 3
Classifier: Development Status :: 3 - Alpha
Classifier: Operating System :: OS Independent
Requires-Python: >=3.13
License-File: LICENSE
Dynamic: license-file
